jaxlayerlumos/__init__.py
jaxlayerlumos/jaxlayerlumos.py
jaxlayerlumos/jaxlayerlumos_old.py
jaxlayerlumos/jaxlayerlumos_old_not_updated.py
jaxlayerlumos/light_sources.json
jaxlayerlumos/materials.json
jaxlayerlumos/utils_layers.py
jaxlayerlumos/utils_light_sources.py
jaxlayerlumos/utils_materials.py
jaxlayerlumos/utils_position.py
jaxlayerlumos/utils_radar_materials.py
jaxlayerlumos/utils_radio_frequency.py
jaxlayerlumos/utils_spectra.py
jaxlayerlumos/utils_units.py
jaxlayerlumos/wrappers.py
jaxlayerlumos/colors/__init__.py
jaxlayerlumos/colors/color_matching_functions.py
jaxlayerlumos/colors/composite.py
jaxlayerlumos/colors/illuminants.py
jaxlayerlumos/colors/transform.py
jaxlayerlumos/colors/utils.py
jaxlayerlumos/light_sources/AM0.csv
jaxlayerlumos/light_sources/AM1p5D.csv
jaxlayerlumos/light_sources/AM1p5G.csv
jaxlayerlumos/materials/AZO-Zarei-2024.csv
jaxlayerlumos/materials/Ag-Rakic-LD-1998.csv
jaxlayerlumos/materials/Air-Peck-1972.csv
jaxlayerlumos/materials/Al-Rakic-LD-1998.csv
jaxlayerlumos/materials/Al2O3-Querry-1985.csv
jaxlayerlumos/materials/Au-Rakic-LD-1998.csv
jaxlayerlumos/materials/BK7-N-BK7.csv
jaxlayerlumos/materials/Cr-Rakic-LD-1998.csv
jaxlayerlumos/materials/Cu-Rakic-LD-1998.csv
jaxlayerlumos/materials/Fe-Werner-DFT-2009.csv
jaxlayerlumos/materials/FusedSilica-Malitson-1965.csv
jaxlayerlumos/materials/GaAs-Rakic-1996.csv
jaxlayerlumos/materials/GaInP-Schubert-1995.csv
jaxlayerlumos/materials/GaP-Adachi-1989.csv
jaxlayerlumos/materials/Ge-Nunley-2016.csv
jaxlayerlumos/materials/ITO-Konig-2014.csv
jaxlayerlumos/materials/ITO-Zarei-2024.csv
jaxlayerlumos/materials/InP-Adachi-1989.csv
jaxlayerlumos/materials/Mg-Palm-2018.csv
jaxlayerlumos/materials/Mn-Querry-1987.csv
jaxlayerlumos/materials/Ni-Rakic-LD-1998.csv
jaxlayerlumos/materials/Pb-Werner-DFT-2009.csv
jaxlayerlumos/materials/Pd-Rakic-LD-1998.csv
jaxlayerlumos/materials/Pt-Rakic-LD-1998.csv
jaxlayerlumos/materials/Sapphire-Malitson-o-1972.csv
jaxlayerlumos/materials/Si3N4-Philipp-1973.csv
jaxlayerlumos-0.3.3.dist-info/licenses/LICENSE
jaxlayerlumos-0.3.3.dist-info/METADATA
jaxlayerlumos-0.3.3.dist-info/WHEEL
jaxlayerlumos-0.3.3.dist-info/top_level.txt
jaxlayerlumos-0.3.3.dist-info/RECORD
