Metadata-Version: 2.4
Name: jaxlayerlumos
Version: 0.3.3
Summary: A JAX-based efficient transfer-matrix method framework for optical simulations
Author-email: Mingxuan Li <mil152@pitt.edu>, Jungtaek Kim <jungtaek.kim.mail@gmail.com>, "Paul W. Leu" <pleu@pitt.edu>
License: MIT
Project-URL: Homepage, https://github.com/JaxLayerLumos/JaxLayerLumos
Project-URL: Source, https://github.com/JaxLayerLumos/JaxLayerLumos
Classifier: Programming Language :: Python :: 3
Classifier: Intended Audience :: Science/Research
Classifier: License :: OSI Approved :: MIT License
Classifier: Operating System :: OS Independent
Classifier: Topic :: Scientific/Engineering
Requires-Python: >=3.8
License-File: LICENSE
Requires-Dist: jax
Requires-Dist: jaxlib
Provides-Extra: dev
Requires-Dist: matplotlib; extra == "dev"
Requires-Dist: pytest; extra == "dev"
Requires-Dist: wheel; extra == "dev"
Requires-Dist: build; extra == "dev"
Requires-Dist: twine; extra == "dev"
Requires-Dist: sphinx; extra == "dev"
Requires-Dist: black; extra == "dev"
Requires-Dist: colour-science; extra == "dev"
Provides-Extra: benchmarking
Requires-Dist: tmm-fast; extra == "benchmarking"
Provides-Extra: examples
Requires-Dist: bayeso; extra == "examples"
Requires-Dist: optax; extra == "examples"
Dynamic: license-file
